sqlalchemy_bigquery/__init__.py
sqlalchemy_bigquery/_helpers.py
sqlalchemy_bigquery/_struct.py
sqlalchemy_bigquery/_types.py
sqlalchemy_bigquery/_versions_helpers.py
sqlalchemy_bigquery/base.py
sqlalchemy_bigquery/geography.py
sqlalchemy_bigquery/parse_url.py
sqlalchemy_bigquery/requirements.py
sqlalchemy_bigquery/version.py
sqlalchemy_bigquery-1.16.0.dist-info/licenses/AUTHORS
sqlalchemy_bigquery-1.16.0.dist-info/licenses/LICENSE
sqlalchemy_bigquery_vendored/__init__.py
sqlalchemy_bigquery_vendored/py.typed
sqlalchemy_bigquery_vendored/sqlalchemy/__init__.py
sqlalchemy_bigquery_vendored/sqlalchemy/postgresql/__init__.py
sqlalchemy_bigquery_vendored/sqlalchemy/postgresql/base.py
sqlalchemy_bigquery-1.16.0.dist-info/METADATA
sqlalchemy_bigquery-1.16.0.dist-info/WHEEL
sqlalchemy_bigquery-1.16.0.dist-info/entry_points.txt
sqlalchemy_bigquery-1.16.0.dist-info/top_level.txt
sqlalchemy_bigquery-1.16.0.dist-info/RECORD
