Metadata-Version: 2.4
Name: sqlalchemy-bigquery
Version: 1.16.0
Summary: SQLAlchemy dialect for BigQuery
Home-page: https://github.com/googleapis/python-bigquery-sqlalchemy
Author: The Sqlalchemy-Bigquery Authors
Author-email: googleapis-packages@google.com
Keywords: bigquery,sqlalchemy
Platform: Posix; MacOS X; Windows
Classifier: Development Status :: 5 - Production/Stable
Classifier: Intended Audience :: Developers
Classifier: License :: OSI Approved :: MIT License
Classifier: Programming Language :: Python
Classifier: Programming Language :: Python :: 3
Classifier: Programming Language :: Python :: 3.8
Classifier: Programming Language :: Python :: 3.9
Classifier: Programming Language :: Python :: 3.10
Classifier: Programming Language :: Python :: 3.11
Classifier: Programming Language :: Python :: 3.12
Classifier: Programming Language :: Python :: 3.13
Classifier: Programming Language :: Python :: 3.14
Classifier: Operating System :: OS Independent
Classifier: Topic :: Database :: Front-Ends
Obsoletes: pybigquery
Requires-Python: >=3.8, <3.15
License-File: LICENSE
License-File: AUTHORS
Requires-Dist: google-api-core!=2.0.*,!=2.1.*,!=2.2.*,!=2.3.0,<3.0.0,>=1.31.5
Requires-Dist: google-auth<3.0.0,>=1.25.0
Requires-Dist: google-cloud-bigquery<4.0.0,>=3.3.6
Requires-Dist: packaging
Requires-Dist: sqlalchemy<3.0.0,>=1.4.16
Provides-Extra: geography
Requires-Dist: GeoAlchemy2; extra == "geography"
Requires-Dist: shapely; extra == "geography"
Provides-Extra: alembic
Requires-Dist: alembic; extra == "alembic"
Provides-Extra: tests
Requires-Dist: packaging; extra == "tests"
Requires-Dist: pytz; extra == "tests"
Provides-Extra: bqstorage
Requires-Dist: google-cloud-bigquery-storage<3.0.0,>=2.0.0; extra == "bqstorage"
Requires-Dist: grpcio<2.0.0,>=1.47.0; extra == "bqstorage"
Requires-Dist: grpcio<2.0.0,>=1.49.1; python_version == "3.11" and extra == "bqstorage"
Requires-Dist: grpcio<2.0.0,>=1.75.1; python_version >= "3.14" and extra == "bqstorage"
Requires-Dist: pyarrow>=5.0.0; extra == "bqstorage"
Provides-Extra: all
Requires-Dist: pytz; extra == "all"
Requires-Dist: google-cloud-bigquery-storage<3.0.0,>=2.0.0; extra == "all"
Requires-Dist: shapely; extra == "all"
Requires-Dist: grpcio<2.0.0,>=1.75.1; python_version >= "3.14" and extra == "all"
Requires-Dist: grpcio<2.0.0,>=1.49.1; python_version == "3.11" and extra == "all"
Requires-Dist: alembic; extra == "all"
Requires-Dist: pyarrow>=5.0.0; extra == "all"
Requires-Dist: GeoAlchemy2; extra == "all"
Requires-Dist: packaging; extra == "all"
Requires-Dist: grpcio<2.0.0,>=1.47.0; extra == "all"
Dynamic: author
Dynamic: author-email
Dynamic: classifier
Dynamic: description
Dynamic: description-content-type
Dynamic: home-page
Dynamic: keywords
Dynamic: license-file
Dynamic: obsoletes
Dynamic: platform
Dynamic: provides-extra
Dynamic: requires-dist
Dynamic: requires-python
Dynamic: summary
